docs/__init__.py
packup/__init__.py
tests/__init__.py
packup-0.1.0.dist-info/LICENSE
packup-0.1.0.dist-info/WHEEL
packup-0.1.0.dist-info/METADATA
packup-0.1.0.dist-info/RECORD
